docassemble/PovertyScale/__init__.py
docassemble/PovertyScale/poverty.py
docassemble/PovertyScale/poverty_endpoint.py
docassemble/PovertyScale/requirements.txt
docassemble/PovertyScale/test_poverty.py
docassemble/PovertyScale/data/questions/demo_poverty_scale.yml
docassemble/PovertyScale/data/questions/poverty.yml
docassemble/PovertyScale/data/sources/README.md
docassemble/PovertyScale/data/sources/federal_poverty_scale.json
docassemble/PovertyScale/data/static/README.md
docassemble/PovertyScale/data/templates/README.md
docassemble_povertyscale-2026.0.0.dist-info/licenses/LICENSE
docassemble_povertyscale-2026.0.0.dist-info/METADATA
docassemble_povertyscale-2026.0.0.dist-info/WHEEL
docassemble_povertyscale-2026.0.0.dist-info/top_level.txt
docassemble_povertyscale-2026.0.0.dist-info/RECORD
