Metadata-Version: 2.4
Name: docassemble.PovertyScale
Version: 2026.0.0
Summary: A docassemble extension.
Home-page: https://github.com/SuffolkLITLab/docassemble-PovertyScale
Author: Quinten Steenhuis
Author-email: qsteenhuis@suffolk.edu
License: The MIT License (MIT)
License-File: LICENSE
Dynamic: author
Dynamic: author-email
Dynamic: description
Dynamic: description-content-type
Dynamic: home-page
Dynamic: license
Dynamic: license-file
Dynamic: summary
